examples/__init__.py
examples/compare_faces.py
examples/detect_faces.py
examples/dominant_language.py
examples/entities.py
examples/generic_entities.py
examples/line.py
examples/table.py
examples/text.py
yapsdk/Yap.py
yapsdk/__init__.py
yapsdk/utils.py
yapsdk/version.py
yapsdk-1.7.0.dist-info/LICENSE
yapsdk-1.7.0.dist-info/METADATA
yapsdk-1.7.0.dist-info/WHEEL
yapsdk-1.7.0.dist-info/top_level.txt
yapsdk-1.7.0.dist-info/RECORD
