Metadata-Version: 2.1
Name: yapsdk
Version: 1.7.0
Summary: Python bindings for the YAP API
Home-page: https://github.com/youngapp/yap-python
Author: youngapp
Author-email: gerardtoko@youngapp.co
License: MIT
Project-URL: Bug Tracker, https://github.com/youngapp/yap-python/issues
Project-URL: Documentation, https://developer.youngapp.co
Project-URL: Source Code, https://github.com/youngapp/yap-python
Keywords: youngapp api machine learning ocr
Platform: UNKNOWN
Classifier: Development Status :: 5 - Production/Stable
Classifier: Intended Audience :: Developers
Classifier: License :: OSI Approved :: MIT License
Classifier: Operating System :: OS Independent
Classifier: Programming Language :: Python
Classifier: Programming Language :: Python :: 2
Classifier: Programming Language :: Python :: 2.7
Classifier: Programming Language :: Python :: 3
Classifier: Programming Language :: Python :: 3.6
Classifier: Programming Language :: Python :: 3.7
Classifier: Programming Language :: Python :: 3.8
Classifier: Programming Language :: Python :: Implementation :: PyPy
Classifier: Topic :: Software Development :: Libraries :: Python Modules
Requires-Python: >=2.7, !=3.0.*, !=3.1.*, !=3.2.*, !=3.3.*, !=3.4.*, !=3.5.*
Requires-Dist: requests[security] (>=2.20) ; python_version < "3.0"
Requires-Dist: requests (>=2.20) ; python_version >= "3.0"
